vale/__init__.py
vale/main.py
vale/vale_bin
vale-3.12.0.2.dist-info/licenses/LICENSE
vale-3.12.0.2.dist-info/METADATA
vale-3.12.0.2.dist-info/WHEEL
vale-3.12.0.2.dist-info/entry_points.txt
vale-3.12.0.2.dist-info/top_level.txt
vale-3.12.0.2.dist-info/RECORD
