Metadata-Version: 2.4
Name: vale
Version: 3.12.0.2
Summary: Install and use Vale (grammar & style check tool) in python environments.
Author: Dani Perez
License: MIT
Project-URL: Homepage, https://github.com/daniperez/vale-python-package
Project-URL: Bug Tracker, https://github.com/daniperez/vale-python-package/issues
Classifier: Programming Language :: Python :: 3
Classifier: License :: OSI Approved :: MIT License
Classifier: Operating System :: OS Independent
Requires-Python: >=3.7
License-File: LICENSE
Dynamic: license-file
